poetry/READ.md
poetry/__init__.py
poetry/cu11_gala.so
poetry/cu_gala.pyd
poetry/cu_gala.so
poetry/cu_gala_d.so
poetry/dataTackle
poetry/dataTackle.exe
poetry/dataTackle.py
poetry/force_field_gala.py
poetry/force_field_gala_hip.py
poetry/force_field_itp.py
poetry/force_field_itp_hip.py
poetry/gala_to_py3.py
poetry/gro_to_xml.py
poetry/hip_gala.so
poetry/hw_config.py
poetry/hw_cu_gala.so
poetry/hw_dataTackle
poetry/hw_molgen.so
poetry/molgen.pyd
poetry/molgen.so
poetry/numerical.py
poetry/numerical_hip.py
poetry/poetry.zip
poetry/win_config.py
pygamd/__init__.py
pygamd/application.py
pygamd/chare.py
pygamd/dump.py
pygamd/force.py
pygamd/integration.py
pygamd/plist.py
pygamd/snapshot.py
pygamd/tinker.py
pygamd/chares/__init__.py
pygamd/chares/compute_properties.py
pygamd/forces/__init__.py
pygamd/forces/angle.py
pygamd/forces/bond.py
pygamd/forces/dihedral.py
pygamd/forces/dpk.py
pygamd/forces/pair.py
pygamd/forces/threebody.py
pygamd/forces/potentials/__init__.py
pygamd/forces/potentials/bonded_library.py
pygamd/forces/potentials/nb_library.py
pygamd/forces/potentials/rng.py
pygamd/integrations/__init__.py
pygamd/integrations/bd.py
pygamd/integrations/dpd.py
pygamd/integrations/nve.py
pygamd/integrations/nvt.py
pygamd/plists/__init__.py
pygamd/plists/clist.py
pygamd/plists/nlist.py
pygamd/plists/vlist.py
pygamd/snapshots/__init__.py
pygamd/snapshots/bonded_data.py
pygamd/snapshots/box.py
pygamd/snapshots/multipole_data.py
pygamd/snapshots/read_mst.py
pygamd/snapshots/read_xml.py
pygamd/tinkers/__init__.py
pygamd/tinkers/hilbert.py
pygamd-1.4.8.dist-info/AUTHORS.rst
pygamd-1.4.8.dist-info/LICENSE
pygamd-1.4.8.dist-info/METADATA
pygamd-1.4.8.dist-info/WHEEL
pygamd-1.4.8.dist-info/top_level.txt
pygamd-1.4.8.dist-info/RECORD
