Metadata-Version: 2.1
Name: pygamd
Version: 1.4.8
Summary: Python GPU-Accelerated Molecular Dynamics Software
Home-page: https://github.com/ylzhu/pygamd.py
Author: You-Liang Zhu
Author-email: ylzhu@pygamd.com
License: GNU General Public License v3 (GPLv3)
Keywords: molecular dynamics
Classifier: Development Status :: 3 - Alpha
Classifier: License :: OSI Approved :: GNU General Public License v3 (GPLv3)
Classifier: Programming Language :: Python :: 3
Classifier: Intended Audience :: Science/Research
Classifier: Operating System :: POSIX :: Linux
Classifier: Topic :: Scientific/Engineering :: Physics
Classifier: Topic :: Scientific/Engineering :: Chemistry
Requires-Python: >=3
License-File: LICENSE
License-File: AUTHORS.rst
Requires-Dist: numpy
Requires-Dist: numba
